ShenduXuexiKuaisuCankaoChuyi/README.md
ShenduXuexiKuaisuCankaoChuyi/__init__.py
ShenduXuexiKuaisuCankaoChuyi/__main__.py
ShenduXuexiKuaisuCankaoChuyi/file.epub
ShenduXuexiKuaisuCankaoChuyi/index.html
ShenduXuexiKuaisuCankaoChuyi/css/__init__.py
ShenduXuexiKuaisuCankaoChuyi/css/annotations.css
ShenduXuexiKuaisuCankaoChuyi/css/main.css
ShenduXuexiKuaisuCankaoChuyi/css/normalize.css
ShenduXuexiKuaisuCankaoChuyi/css/popup.css
ShenduXuexiKuaisuCankaoChuyi/font/__init__.py
ShenduXuexiKuaisuCankaoChuyi/font/fontello.eot
ShenduXuexiKuaisuCankaoChuyi/font/fontello.svg
ShenduXuexiKuaisuCankaoChuyi/font/fontello.ttf
ShenduXuexiKuaisuCankaoChuyi/font/fontello.woff
ShenduXuexiKuaisuCankaoChuyi/img/__init__.py
ShenduXuexiKuaisuCankaoChuyi/img/annotator-glyph-sprite.png
ShenduXuexiKuaisuCankaoChuyi/img/annotator-icon-sprite.png
ShenduXuexiKuaisuCankaoChuyi/img/apple-touch-icon.png
ShenduXuexiKuaisuCankaoChuyi/img/cancelfullscreen.png
ShenduXuexiKuaisuCankaoChuyi/img/close.png
ShenduXuexiKuaisuCankaoChuyi/img/fullscreen.png
ShenduXuexiKuaisuCankaoChuyi/img/loader.gif
ShenduXuexiKuaisuCankaoChuyi/img/menu-icon.png
ShenduXuexiKuaisuCankaoChuyi/img/save.png
ShenduXuexiKuaisuCankaoChuyi/img/saved.png
ShenduXuexiKuaisuCankaoChuyi/img/settings-s.png
ShenduXuexiKuaisuCankaoChuyi/img/settings.png
ShenduXuexiKuaisuCankaoChuyi/img/star.png
ShenduXuexiKuaisuCankaoChuyi/js/__init__.py
ShenduXuexiKuaisuCankaoChuyi/js/epub.js
ShenduXuexiKuaisuCankaoChuyi/js/epub.min.js
ShenduXuexiKuaisuCankaoChuyi/js/epub.min.map
ShenduXuexiKuaisuCankaoChuyi/js/hooks.min.js
ShenduXuexiKuaisuCankaoChuyi/js/hooks.min.map
ShenduXuexiKuaisuCankaoChuyi/js/reader.js
ShenduXuexiKuaisuCankaoChuyi/js/reader.js.map
ShenduXuexiKuaisuCankaoChuyi/js/reader.min.js
ShenduXuexiKuaisuCankaoChuyi/js/reader.min.map
ShenduXuexiKuaisuCankaoChuyi/js/hooks/__init__.py
ShenduXuexiKuaisuCankaoChuyi/js/hooks/extensions/__init__.py
ShenduXuexiKuaisuCankaoChuyi/js/hooks/extensions/highlight.js
shendu_xuexi_kuaisu_cankao_chuyi-2024.3.5.0.dist-info/METADATA
shendu_xuexi_kuaisu_cankao_chuyi-2024.3.5.0.dist-info/WHEEL
shendu_xuexi_kuaisu_cankao_chuyi-2024.3.5.0.dist-info/entry_points.txt
shendu_xuexi_kuaisu_cankao_chuyi-2024.3.5.0.dist-info/top_level.txt
shendu_xuexi_kuaisu_cankao_chuyi-2024.3.5.0.dist-info/RECORD
